errorvision/Logger.py
errorvision/__init__.py
errorvision/ai.py
errorvision/core.py
errorvision-0.0.3.dist-info/LICENSE
errorvision-0.0.3.dist-info/METADATA
errorvision-0.0.3.dist-info/WHEEL
errorvision-0.0.3.dist-info/top_level.txt
errorvision-0.0.3.dist-info/RECORD
