Metadata-Version: 2.1
Name: errorvision
Version: 0.0.3
Summary: A small python package
Home-page: https://github.com/muhaiminulsadat/ErrorVision-PyPI-Package
Author: muhaiminulsadat
Author-email: muhaiminulsadat@gmail.com
License: MIT
Project-URL: Bug Tracker, https://github.com/muhaiminulsadat/ErrorVision-PyPI-Package/issues
Classifier: Programming Language :: Python :: 3.8
Classifier: Programming Language :: Python :: 3.9
Classifier: Operating System :: OS Independent
License-File: LICENSE
Requires-Dist: colorama==0.4.6
Requires-Dist: dotenv
Provides-Extra: testing
Requires-Dist: pytest>=7.1.3; extra == "testing"
Requires-Dist: mypy>=0.971; extra == "testing"
Requires-Dist: flake8>=5.0.4; extra == "testing"
Requires-Dist: tox>=3.25.1; extra == "testing"
